LICENSE
MANIFEST.in
README.md
requirements.txt
setup.cfg
setup.py
bluebox/__init__.py
bluebox/bluebox.py
bluebox.egg-info/PKG-INFO
bluebox.egg-info/SOURCES.txt
bluebox.egg-info/dependency_links.txt
bluebox.egg-info/not-zip-safe
bluebox.egg-info/top_level.txt