Metadata-Version: 2.1
Name: bluebox
Version: 0.0.1
Summary: python package practice
Home-page: https://github.com/olilamm/bluebox
Author: Olivia Lamm
Author-email: olamm@vols.utk.edu
License: MIT license
Keywords: bluebox
Classifier: Development Status :: 2 - Pre-Alpha
Classifier: Intended Audience :: Developers
Classifier: License :: OSI Approved :: MIT License
Classifier: Natural Language :: English
Classifier: Programming Language :: Python :: 3
Classifier: Programming Language :: Python :: 3.7
Classifier: Programming Language :: Python :: 3.8
Classifier: Programming Language :: Python :: 3.9
Classifier: Programming Language :: Python :: 3.10
Requires-Python: >=3.7
License-File: LICENSE
